{
  "ok": true,
  "fetchedAt": "2026-07-11T04:55:11.064Z",
  "range": "last_7_days",
  "humanReadableTotal": "21 hrs 9 mins",
  "humanReadableDailyAverage": "3 hrs 1 min",
  "totalSeconds": 76149.525,
  "dailyAverage": 10879,
  "languages": [
    {
      "name": "Go",
      "percent": 70.5,
      "text": "15 hrs 21 mins"
    },
    {
      "name": "SQL",
      "percent": 13.74,
      "text": "2 hrs 59 mins"
    },
    {
      "name": "Bash",
      "percent": 7.51,
      "text": "1 hr 38 mins"
    },
    {
      "name": "Other",
      "percent": 2.9,
      "text": "37 mins"
    },
    {
      "name": "YAML",
      "percent": 1.4,
      "text": "18 mins"
    },
    {
      "name": "go.mod",
      "percent": 1.28,
      "text": "16 mins"
    },
    {
      "name": "textmate",
      "percent": 1.13,
      "text": "14 mins"
    },
    {
      "name": "Makefile",
      "percent": 1.12,
      "text": "14 mins"
    },
    {
      "name": "HTML",
      "percent": 0.36,
      "text": "4 mins"
    },
    {
      "name": "Markdown",
      "percent": 0.02,
      "text": "0 secs"
    }
  ],
  "editors": [
    {
      "name": "VS Code",
      "percent": 60.44,
      "text": "13 hrs 9 mins"
    },
    {
      "name": "GoLand",
      "percent": 29.45,
      "text": "6 hrs 24 mins"
    },
    {
      "name": "DataGrip",
      "percent": 10.11,
      "text": "2 hrs 12 mins"
    }
  ],
  "operatingSystems": [
    {
      "name": "Linux",
      "percent": 100,
      "text": "21 hrs 47 mins"
    }
  ],
  "projects": [
    {
      "name": "cbs-backend",
      "percent": 89.29,
      "text": "19 hrs 27 mins"
    },
    {
      "name": "renesans",
      "percent": 8.24,
      "text": "1 hr 47 mins"
    },
    {
      "name": "IntelliJIdea2026.1",
      "percent": 0.85,
      "text": "11 mins"
    },
    {
      "name": "kilo-test",
      "percent": 0.84,
      "text": "10 mins"
    },
    {
      "name": "Desktop",
      "percent": 0.56,
      "text": "7 mins"
    }
  ],
  "categories": [
    {
      "name": "Coding",
      "percent": 53.25,
      "text": "11 hrs 36 mins"
    },
    {
      "name": "AI Coding",
      "percent": 46.7,
      "text": "10 hrs 10 mins"
    },
    {
      "name": "Writing Docs",
      "percent": 0.02,
      "text": "0 secs"
    },
    {
      "name": "Writing Tests",
      "percent": 0.02,
      "text": "0 secs"
    }
  ],
  "allTime": "885 hrs 2 mins",
  "allTimeLanguages": [
    {
      "name": "Go",
      "percent": 61.69,
      "text": "545 hrs 59 mins"
    },
    {
      "name": "TypeScript",
      "percent": 12.17,
      "text": "107 hrs 41 mins"
    },
    {
      "name": "PHP",
      "percent": 5.44,
      "text": "48 hrs 6 mins"
    },
    {
      "name": "SQL",
      "percent": 4.09,
      "text": "36 hrs 9 mins"
    },
    {
      "name": "YAML",
      "percent": 3.26,
      "text": "28 hrs 49 mins"
    }
  ],
  "allTimeEditors": [
    {
      "name": "GoLand",
      "percent": 44.17,
      "text": "390 hrs 56 mins"
    },
    {
      "name": "VS Code",
      "percent": 34.92,
      "text": "309 hrs 4 mins"
    },
    {
      "name": "PhpStorm",
      "percent": 5.75,
      "text": "50 hrs 51 mins"
    }
  ],
  "allTimeOS": [
    {
      "name": "Linux",
      "percent": 78.57,
      "text": "695 hrs 22 mins"
    },
    {
      "name": "Windows",
      "percent": 21.43,
      "text": "189 hrs 39 mins"
    }
  ],
  "allTimeTotalSeconds": 3124125.395
}